asmreader/__init__.py
asmreader/__main__.py
asmreader/audio_processor.py
asmreader/cli.py
asmreader/download_model.py
asmreader/py.typed
asmreader/utils.py
asmreader/readers/__init__.py
asmreader/readers/base.py
asmreader/readers/epub_reader.py
asmreader/readers/markdown_reader.py
asmreader/readers/pdf_reader.py
asmreader/readers/txt_reader.py
asmreader/readers/web_reader.py
asmreader-0.1.2.dist-info/METADATA
asmreader-0.1.2.dist-info/WHEEL
asmreader-0.1.2.dist-info/entry_points.txt
asmreader-0.1.2.dist-info/licenses/LICENSE
asmreader-0.1.2.dist-info/RECORD
