Metadata-Version: 2.4
Name: asmreader
Version: 0.1.2
Summary: Turn any text into a soothing ASMR-style reading experience
Author-email: Autoscatto <4utoscatto@gmail.com>
License-Expression: MIT
License-File: LICENSE
Keywords: asmr,pdf,reader,text-to-speech,tts
Classifier: Development Status :: 4 - Beta
Classifier: Environment :: Console
Classifier: Intended Audience :: End Users/Desktop
Classifier: License :: OSI Approved :: MIT License
Classifier: Programming Language :: Python :: 3.11
Classifier: Topic :: Multimedia :: Sound/Audio :: Speech
Classifier: Topic :: Text Processing :: General
Classifier: Typing :: Typed
Requires-Python: >=3.11
Requires-Dist: beautifulsoup4>=4.12.3
Requires-Dist: ebooklib>=0.18
Requires-Dist: kokoro-onnx>=0.3.5
Requires-Dist: lxml[html-clean]>=5.3.0
Requires-Dist: markdown>=3.7
Requires-Dist: pypdf>=3.17.1
Requires-Dist: python-magic>=0.4.27
Requires-Dist: readability-lxml>=0.8.1
Requires-Dist: requests>=2.32.3
Requires-Dist: simpleaudio>=1.0.4
Requires-Dist: sounddevice>=0.5.1
Requires-Dist: soundfile>=0.13.0
Requires-Dist: tdqm>=0.0.1
Provides-Extra: dev
Requires-Dist: black>=24.1.1; extra == 'dev'
Requires-Dist: mypy>=1.8.0; extra == 'dev'
Requires-Dist: pytest-cov>=4.1.0; extra == 'dev'
Requires-Dist: pytest>=7.4.0; extra == 'dev'
Requires-Dist: responses>=0.24.1; extra == 'dev'
Requires-Dist: ruff>=0.2.1; extra == 'dev'
Requires-Dist: types-beautifulsoup4; extra == 'dev'
Requires-Dist: types-markdown; extra == 'dev'
Requires-Dist: types-requests; extra == 'dev'
Requires-Dist: types-tqdm>=4.67.0.20241221; extra == 'dev'
